crimson/__init__.py
crimson/assets_fetch.py
crimson/atlas.py
crimson/audio_router.py
crimson/bonuses.py
crimson/camera.py
crimson/cli.py
crimson/creatures/__init__.py
crimson/creatures/ai.py
crimson/creatures/anim.py
crimson/creatures/damage.py
crimson/creatures/runtime.py
crimson/creatures/spawn.py
crimson/debug.py
crimson/demo.py
crimson/demo_trial.py
crimson/effects.py
crimson/effects_atlas.py
crimson/frontend/__init__.py
crimson/frontend/assets.py
crimson/frontend/boot.py
crimson/frontend/menu.py
crimson/frontend/panels/__init__.py
crimson/frontend/panels/base.py
crimson/frontend/panels/controls.py
crimson/frontend/panels/mods.py
crimson/frontend/panels/options.py
crimson/frontend/panels/play_game.py
crimson/frontend/panels/stats.py
crimson/frontend/transitions.py
crimson/game.py
crimson/game_modes.py
crimson/game_world.py
crimson/gameplay.py
crimson/input_codes.py
crimson/modes/__init__.py
crimson/modes/base_gameplay_mode.py
crimson/modes/quest_mode.py
crimson/modes/rush_mode.py
crimson/modes/survival_mode.py
crimson/modes/tutorial_mode.py
crimson/modes/typo_mode.py
crimson/paths.py
crimson/perks.py
crimson/persistence/__init__.py
crimson/persistence/highscores.py
crimson/persistence/save_status.py
crimson/player_damage.py
crimson/projectiles.py
crimson/quests/__init__.py
crimson/quests/helpers.py
crimson/quests/registry.py
crimson/quests/results.py
crimson/quests/runtime.py
crimson/quests/tier1.py
crimson/quests/tier2.py
crimson/quests/tier3.py
crimson/quests/tier4.py
crimson/quests/tier5.py
crimson/quests/timeline.py
crimson/quests/types.py
crimson/render/__init__.py
crimson/render/terrain_fx.py
crimson/render/world_renderer.py
crimson/sim/__init__.py
crimson/sim/world_defs.py
crimson/sim/world_state.py
crimson/terrain_assets.py
crimson/tutorial/__init__.py
crimson/tutorial/timeline.py
crimson/typo/__init__.py
crimson/typo/names.py
crimson/typo/player.py
crimson/typo/spawns.py
crimson/typo/typing.py
crimson/ui/__init__.py
crimson/ui/cursor.py
crimsonland-0.1.0.dev11.dist-info/WHEEL
crimsonland-0.1.0.dev11.dist-info/entry_points.txt
crimsonland-0.1.0.dev11.dist-info/METADATA
crimsonland-0.1.0.dev11.dist-info/RECORD
