Metadata-Version: 2.3
Name: crimsonland
Version: 0.1.0.dev11
Requires-Dist: construct>=2.10.70
Requires-Dist: pillow>=12.1.0
Requires-Dist: platformdirs>=4.5.1
Requires-Dist: raylib>=5.5.0.4
Requires-Dist: typer>=0.21.1
Requires-Python: >=3.13
